akbs/__main__.py
akbs-1.0.5.dist-info/LICENSE
akbs-1.0.5.dist-info/METADATA
akbs-1.0.5.dist-info/WHEEL
akbs-1.0.5.dist-info/top_level.txt
akbs-1.0.5.dist-info/RECORD
