Metadata-Version: 2.1
Name: akbs
Version: 1.0.5
Summary: A super quick build system for C, C++ and ASM
Author-email: Aarav Malani <aarav.malani@gmail.com>
Project-URL: Homepage, https://github.com/AaravMalani/AKBS
Project-URL: Bug Tracker, https://github.com/AaravMalani/AKBS/issues
Classifier: Programming Language :: Python :: 3
Classifier: License :: OSI Approved :: MIT License
Classifier: Operating System :: Unix
Requires-Python: >=3.8
License-File: LICENSE
